pdkmaster-0.12.0.dist-info/METADATA
pdkmaster-0.12.0.dist-info/WHEEL
pdkmaster-0.12.0.dist-info/entry_points.txt
pdkmaster-0.12.0.dist-info/licenses/LICENSE.md
pdkmaster/_util.py
pdkmaster/design/__init__.py
pdkmaster/design/cell.py
pdkmaster/design/circuit.py
pdkmaster/design/factory.py
pdkmaster/design/layout/__init__.py
pdkmaster/design/layout/_circuitlayouter.py
pdkmaster/design/layout/_primitivelayouter.py
pdkmaster/design/layout/factory_.py
pdkmaster/design/layout/layout_.py
pdkmaster/design/library.py
pdkmaster/design/routinggauge.py
pdkmaster/dispatch/__init__.py
pdkmaster/dispatch/edge.py
pdkmaster/dispatch/mask.py
pdkmaster/dispatch/primitive.py
pdkmaster/dispatch/rule.py
pdkmaster/dispatch/shape.py
pdkmaster/task.py
pdkmaster/technology/__init__.py
pdkmaster/technology/edge.py
pdkmaster/technology/geometry.py
pdkmaster/technology/mask.py
pdkmaster/technology/net.py
pdkmaster/technology/primitive/__init__.py
pdkmaster/technology/primitive/_core.py
pdkmaster/technology/primitive/_derived.py
pdkmaster/technology/primitive/_param.py
pdkmaster/technology/primitive/conductors.py
pdkmaster/technology/primitive/devices.py
pdkmaster/technology/primitive/layers.py
pdkmaster/technology/primitive/rules.py
pdkmaster/technology/property_.py
pdkmaster/technology/rule.py
pdkmaster/technology/technology_.py
pdkmaster/technology/wafer_.py
pdkmaster/test/dummytech/__init__.py
pdkmaster/test/dummytech/gds.py
pdkmaster/test/dummytech/lib.py
pdkmaster/test/dummytech/tech.py
pdkmaster/typing.py
pdkmaster-0.12.0.dist-info/RECORD
