Metadata-Version: 2.1
Name: PDKMaster
Version: 0.12.0
Summary: ASIC PDK Manager and Design Framework
Author: Chips4Makers contributors
License: GPL-2.0-or-later OR AGPL-3.0-or-later OR CERN-OHL-S-2.0+
Requires-Python: ~=3.8
